gemican/__init__.py
gemican/__main__.py
gemican/cache.py
gemican/contents.py
gemican/generators.py
gemican/log.py
gemican/paginator.py
gemican/plugins/_utils.py
gemican/plugins/signals.py
gemican/readers.py
gemican/server.py
gemican/settings.py
gemican/signals.py
gemican/tests/TestPages/bad_page.gmi
gemican/tests/TestPages/draft_page.gmi
gemican/tests/TestPages/draft_page_markdown.gmi
gemican/tests/TestPages/draft_page_with_template.gmi
gemican/tests/TestPages/hidden_page.gmi
gemican/tests/TestPages/hidden_page_markdown.gmi
gemican/tests/TestPages/hidden_page_with_template.gmi
gemican/tests/TestPages/page.gmi
gemican/tests/TestPages/page_markdown.gmi
gemican/tests/TestPages/page_used_for_sorting_test.gmi
gemican/tests/TestPages/page_with_category_and_tag_links.gmi
gemican/tests/TestPages/page_with_static_links.gmi
gemican/tests/TestPages/page_with_template.gmi
gemican/tests/__init__.py
gemican/tests/content/2012-11-29_gmi_w_filename_meta#foo-bar.gmi
gemican/tests/content/2012-11-30_md_w_filename_meta#foo-bar.md
gemican/tests/content/TestCategory/article_with_category.gmi
gemican/tests/content/TestCategory/article_without_category.gmi
gemican/tests/content/article.gmi
gemican/tests/content/article_draft.gmi
gemican/tests/content/article_hidden.gmi
gemican/tests/content/article_with_attributes_containing_double_quotes.html
gemican/tests/content/article_with_capitalized_metadata.gmi
gemican/tests/content/article_with_code_block.gmi
gemican/tests/content/article_with_comments.html
gemican/tests/content/article_with_duplicate_tags_authors.gmi
gemican/tests/content/article_with_duplicate_tags_authors.md
gemican/tests/content/article_with_inline_svg.html
gemican/tests/content/article_with_keywords.html
gemican/tests/content/article_with_markdown_and_footnote.md
gemican/tests/content/article_with_markdown_and_nested_metadata.md
gemican/tests/content/article_with_markdown_and_nonascii_summary.md
gemican/tests/content/article_with_markdown_and_summary_metadata_multi.md
gemican-5.0.1.dist-info/entry_points.txt
gemican-5.0.1.dist-info/LICENSE
gemican-5.0.1.dist-info/WHEEL
gemican-5.0.1.dist-info/METADATA
gemican-5.0.1.dist-info/RECORD
